nuts/__init__.py
nuts/base_tests/__init__.py
nuts/base_tests/napalm_bgp_neighbors.py
nuts/base_tests/napalm_get_arp.py
nuts/base_tests/napalm_get_config.py
nuts/base_tests/napalm_get_users.py
nuts/base_tests/napalm_get_vlans.py
nuts/base_tests/napalm_interfaces.py
nuts/base_tests/napalm_lldp_neighbors.py
nuts/base_tests/napalm_network_instances.py
nuts/base_tests/napalm_ping.py
nuts/base_tests/netmiko_cdp_neighbors.py
nuts/base_tests/netmiko_iperf.py
nuts/base_tests/netmiko_ospf_neighbors.py
nuts/context.py
nuts/helpers/__init__.py
nuts/helpers/cache.py
nuts/helpers/context.py
nuts/helpers/converters.py
nuts/helpers/errors.py
nuts/helpers/filters.py
nuts/helpers/result.py
nuts/hooks.py
nuts/index.py
nuts/nuts_init.py
nuts/plugin.py
nuts/yamlloader.py
nuts-3.5.1.dist-info/METADATA
nuts-3.5.1.dist-info/WHEEL
nuts-3.5.1.dist-info/entry_points.txt
nuts-3.5.1.dist-info/licenses/LICENSE
nuts-3.5.1.dist-info/RECORD
