Metadata-Version: 2.4
Name: nuts
Version: 3.5.1
Summary: Network Unit Testing System
License: MIT
License-File: LICENSE
Author: Lukas Murer, Méline Sieber, Urs Baumann, Matthias Gabriel, Florian Bruhin
Maintainer: Marco Martinez
Maintainer-email: marco.maritnez@ost.ch
Requires-Python: >=3.9,<4.0
Classifier: Framework :: Pytest
Classifier: License :: OSI Approved :: MIT License
Classifier: Programming Language :: Python :: 3
Classifier: Programming Language :: Python :: 3.9
Classifier: Programming Language :: Python :: 3.10
Classifier: Programming Language :: Python :: 3.11
Classifier: Programming Language :: Python :: 3.12
Classifier: Programming Language :: Python :: 3.13
Classifier: Programming Language :: Python :: 3.14
Classifier: Topic :: System :: Networking
Requires-Dist: PyYAML (>=6.0,<7.0)
Requires-Dist: nornir (>=3.3.0,<4.0.0)
Requires-Dist: nornir-napalm (>=0.5.0,<0.6.0)
Requires-Dist: nornir-netmiko (>=1.0.0,<2.0.0)
Requires-Dist: nornir-utils (>=0.2.0,<0.3.0)
Requires-Dist: pytest (>=7,<8)
Requires-Dist: rich (>=14.0.0,<15.0.0)
Requires-Dist: ruamel-yaml (>=0.18.10,<0.19.0)
Requires-Dist: typer (>=0.15.3,<0.16.0)
Project-URL: Homepage, https://github.com/network-unit-testing-system/nuts
Project-URL: Repository, https://github.com/network-unit-testing-system/nuts
